Workbook
Name AgentNameList: '👤 Agents'!$C$4:$C$38

Sheet 📊 Dashboard
A1: 📊 HH REALTY — TRANSACTION DASHBOARD
A2: =CONCATENATE("Last Updated: ",TEXT(NOW(),"mmmm d, yyyy h:MM AM/PM"))
A3: KEY PERFORMANCE INDICATORS
B4: 📈 ACTIVE TRANSACTIONS | C4: 💰 TOTAL HH REVENUE | D4: 📅 CLOSING ≤ 7 DAYS | E4: ⚠️ COMMISSION ISSUES
B5: =COUNTIF('🗄️ Transactions'!Y5:Y200,"Active") | C5: =SUMIF('🗄️ Transactions'!Y5:Y200,"Active",'🗄️ Transactions'!AI5:AI200) | D5: =COUNTIFS('🗄️ Transactions'!H5:H200,">="&TODAY(),'🗄️ Transactions'!H5:H200,"<="&(TODAY()+7),'🗄️ Transactions'!Y5:Y200,"Active") | E5: =COUNTIF('🗄️ Transactions'!AJ5:AJ200,"*CHECK*")
B8: ✅ CLOSED THIS YEAR | C8: 💼 CLOSINGS THIS MONTH | D8: 🏦 MISSING TITLE CO. | E8: 💣 BOMB TRANSACTIONS
B9: =COUNTIF('🗄️ Transactions'!Y5:Y200,"Closed") | C9: =COUNTIFS('🗄️ Transactions'!H5:H200,">="&EOMONTH(TODAY(),-1)+1,'🗄️ Transactions'!H5:H200,"<="&EOMONTH(TODAY(),0),'🗄️ Transactions'!Y5:Y200,"Active") | D9: =COUNTIFS('🗄️ Transactions'!V5:V200,"",'🗄️ Transactions'!Y5:Y200,"Active") | E9: =COUNTIF('🗄️ Transactions'!Y5:Y200,"BOMB")
B12: 📅 CLOSING WITHIN 14 DAYS
B13: Txn ID | C13: Address | D13: Closing Date | E13: Days Left
B14: =IFERROR(INDEX('🗄️ Transactions'!$A$5:$A$200,MATCH(SMALL(IF('🗄️ Transactions'!$Y$5:$Y$200="Active",IF('🗄️ Transactions'!$H$5:$H$200>=TODAY()-1,'🗄️ Transactions'!$H$5:$H$200,9999999)),1),'🗄️ Transactions'!$H$5:$H$200,0)),"—") | C14: =IFERROR(INDEX('🗄️ Transactions'!$C$5:$C$200,MATCH(SMALL(IF('🗄️ Transactions'!$Y$5:$Y$200="Active",IF('🗄️ Transactions'!$H$5:$H$200>=TODAY()-1,'🗄️ Transactions'!$H$5:$H$200,9999999)),1),'🗄️ Transactions'!$H$5:$H$200,0)),"—") | D14: =IFERROR(SMALL(IF('🗄️ Transactions'!$Y$5:$Y$200="Active",IF('🗄️ Transactions'!$H$5:$H$200>=TODAY()-1,'🗄️ Transactions'!$H$5:$H$200,9999999)),1),"—") | E14: =IFERROR(D14-TODAY(),"—")
B15: =IFERROR(INDEX('🗄️ Transactions'!$A$5:$A$200,MATCH(SMALL(IF('🗄️ Transactions'!$Y$5:$Y$200="Active",IF('🗄️ Transactions'!$H$5:$H$200>=TODAY()-1,'🗄️ Transactions'!$H$5:$H$200,9999999)),2),'🗄️ Transactions'!$H$5:$H$200,0)),"—") | C15: =IFERROR(INDEX('🗄️ Transactions'!$C$5:$C$200,MATCH(SMALL(IF('🗄️ Transactions'!$Y$5:$Y$200="Active",IF('🗄️ Transactions'!$H$5:$H$200>=TODAY()-1,'🗄️ Transactions'!$H$5:$H$200,9999999)),2),'🗄️ Transactions'!$H$5:$H$200,0)),"—") | D15: =IFERROR(SMALL(IF('🗄️ Transactions'!$Y$5:$Y$200="Active",IF('🗄️ Transactions'!$H$5:$H$200>=TODAY()-1,'🗄️ Transactions'!$H$5:$H$200,9999999)),2),"—") | E15: =IFERROR(D15-TODAY(),"—")
B16: =IFERROR(INDEX('🗄️ Transactions'!$A$5:$A$200,MATCH(SMALL(IF('🗄️ Transactions'!$Y$5:$Y$200="Active",IF('🗄️ Transactions'!$H$5:$H$200>=TODAY()-1,'🗄️ Transactions'!$H$5:$H$200,9999999)),3),'🗄️ Transactions'!$H$5:$H$200,0)),"—") | C16: =IFERROR(INDEX('🗄️ Transactions'!$C$5:$C$200,MATCH(SMALL(IF('🗄️ Transactions'!$Y$5:$Y$200="Active",IF('🗄️ Transactions'!$H$5:$H$200>=TODAY()-1,'🗄️ Transactions'!$H$5:$H$200,9999999)),3),'🗄️ Transactions'!$H$5:$H$200,0)),"—") | D16: =IFERROR(SMALL(IF('🗄️ Transactions'!$Y$5:$Y$200="Active",IF('🗄️ Transactions'!$H$5:$H$200>=TODAY()-1,'🗄️ Transactions'!$H$5:$H$200,9999999)),3),"—") | E16: =IFERROR(D16-TODAY(),"—")
B17: =IFERROR(INDEX('🗄️ Transactions'!$A$5:$A$200,MATCH(SMALL(IF('🗄️ Transactions'!$Y$5:$Y$200="Active",IF('🗄️ Transactions'!$H$5:$H$200>=TODAY()-1,'🗄️ Transactions'!$H$5:$H$200,9999999)),4),'🗄️ Transactions'!$H$5:$H$200,0)),"—") | C17: =IFERROR(INDEX('🗄️ Transactions'!$C$5:$C$200,MATCH(SMALL(IF('🗄️ Transactions'!$Y$5:$Y$200="Active",IF('🗄️ Transactions'!$H$5:$H$200>=TODAY()-1,'🗄️ Transactions'!$H$5:$H$200,9999999)),4),'🗄️ Transactions'!$H$5:$H$200,0)),"—") | D17: =IFERROR(SMALL(IF('🗄️ Transactions'!$Y$5:$Y$200="Active",IF('🗄️ Transactions'!$H$5:$H$200>=TODAY()-1,'🗄️ Transactions'!$H$5:$H$200,9999999)),4),"—") | E17: =IFERROR(D17-TODAY(),"—")
B18: =IFERROR(INDEX('🗄️ Transactions'!$A$5:$A$200,MATCH(SMALL(IF('🗄️ Transactions'!$Y$5:$Y$200="Active",IF('🗄️ Transactions'!$H$5:$H$200>=TODAY()-1,'🗄️ Transactions'!$H$5:$H$200,9999999)),5),'🗄️ Transactions'!$H$5:$H$200,0)),"—") | C18: =IFERROR(INDEX('🗄️ Transactions'!$C$5:$C$200,MATCH(SMALL(IF('🗄️ Transactions'!$Y$5:$Y$200="Active",IF('🗄️ Transactions'!$H$5:$H$200>=TODAY()-1,'🗄️ Transactions'!$H$5:$H$200,9999999)),5),'🗄️ Transactions'!$H$5:$H$200,0)),"—") | D18: =IFERROR(SMALL(IF('🗄️ Transactions'!$Y$5:$Y$200="Active",IF('🗄️ Transactions'!$H$5:$H$200>=TODAY()-1,'🗄️ Transactions'!$H$5:$H$200,9999999)),5),"—") | E18: =IFERROR(D18-TODAY(),"—")
B19: =IFERROR(INDEX('🗄️ Transactions'!$A$5:$A$200,MATCH(SMALL(IF('🗄️ Transactions'!$Y$5:$Y$200="Active",IF('🗄️ Transactions'!$H$5:$H$200>=TODAY()-1,'🗄️ Transactions'!$H$5:$H$200,9999999)),6),'🗄️ Transactions'!$H$5:$H$200,0)),"—") | C19: =IFERROR(INDEX('🗄️ Transactions'!$C$5:$C$200,MATCH(SMALL(IF('🗄️ Transactions'!$Y$5:$Y$200="Active",IF('🗄️ Transactions'!$H$5:$H$200>=TODAY()-1,'🗄️ Transactions'!$H$5:$H$200,9999999)),6),'🗄️ Transactions'!$H$5:$H$200,0)),"—") | D19: =IFERROR(SMALL(IF('🗄️ Transactions'!$Y$5:$Y$200="Active",IF('🗄️ Transactions'!$H$5:$H$200>=TODAY()-1,'🗄️ Transactions'!$H$5:$H$200,9999999)),6),"—") | E19: =IFERROR(D19-TODAY(),"—")
B20: =IFERROR(INDEX('🗄️ Transactions'!$A$5:$A$200,MATCH(SMALL(IF('🗄️ Transactions'!$Y$5:$Y$200="Active",IF('🗄️ Transactions'!$H$5:$H$200>=TODAY()-1,'🗄️ Transactions'!$H$5:$H$200,9999999)),7),'🗄️ Transactions'!$H$5:$H$200,0)),"—") | C20: =IFERROR(INDEX('🗄️ Transactions'!$C$5:$C$200,MATCH(SMALL(IF('🗄️ Transactions'!$Y$5:$Y$200="Active",IF('🗄️ Transactions'!$H$5:$H$200>=TODAY()-1,'🗄️ Transactions'!$H$5:$H$200,9999999)),7),'🗄️ Transactions'!$H$5:$H$200,0)),"—") | D20: =IFERROR(SMALL(IF('🗄️ Transactions'!$Y$5:$Y$200="Active",IF('🗄️ Transactions'!$H$5:$H$200>=TODAY()-1,'🗄️ Transactions'!$H$5:$H$200,9999999)),7),"—") | E20: =IFERROR(D20-TODAY(),"—")
B21: =IFERROR(INDEX('🗄️ Transactions'!$A$5:$A$200,MATCH(SMALL(IF('🗄️ Transactions'!$Y$5:$Y$200="Active",IF('🗄️ Transactions'!$H$5:$H$200>=TODAY()-1,'🗄️ Transactions'!$H$5:$H$200,9999999)),8),'🗄️ Transactions'!$H$5:$H$200,0)),"—") | C21: =IFERROR(INDEX('🗄️ Transactions'!$C$5:$C$200,MATCH(SMALL(IF('🗄️ Transactions'!$Y$5:$Y$200="Active",IF('🗄️ Transactions'!$H$5:$H$200>=TODAY()-1,'🗄️ Transactions'!$H$5:$H$200,9999999)),8),'🗄️ Transactions'!$H$5:$H$200,0)),"—") | D21: =IFERROR(SMALL(IF('🗄️ Transactions'!$Y$5:$Y$200="Active",IF('🗄️ Transactions'!$H$5:$H$200>=TODAY()-1,'🗄️ Transactions'!$H$5:$H$200,9999999)),8),"—") | E21: =IFERROR(D21-TODAY(),"—")
B22: =IFERROR(INDEX('🗄️ Transactions'!$A$5:$A$200,MATCH(SMALL(IF('🗄️ Transactions'!$Y$5:$Y$200="Active",IF('🗄️ Transactions'!$H$5:$H$200>=TODAY()-1,'🗄️ Transactions'!$H$5:$H$200,9999999)),9),'🗄️ Transactions'!$H$5:$H$200,0)),"—") | C22: =IFERROR(INDEX('🗄️ Transactions'!$C$5:$C$200,MATCH(SMALL(IF('🗄️ Transactions'!$Y$5:$Y$200="Active",IF('🗄️ Transactions'!$H$5:$H$200>=TODAY()-1,'🗄️ Transactions'!$H$5:$H$200,9999999)),9),'🗄️ Transactions'!$H$5:$H$200,0)),"—") | D22: =IFERROR(SMALL(IF('🗄️ Transactions'!$Y$5:$Y$200="Active",IF('🗄️ Transactions'!$H$5:$H$200>=TODAY()-1,'🗄️ Transactions'!$H$5:$H$200,9999999)),9),"—") | E22: =IFERROR(D22-TODAY(),"—")
B23: =IFERROR(INDEX('🗄️ Transactions'!$A$5:$A$200,MATCH(SMALL(IF('🗄️ Transactions'!$Y$5:$Y$200="Active",IF('🗄️ Transactions'!$H$5:$H$200>=TODAY()-1,'🗄️ Transactions'!$H$5:$H$200,9999999)),10),'🗄️ Transactions'!$H$5:$H$200,0)),"—") | C23: =IFERROR(INDEX('🗄️ Transactions'!$C$5:$C$200,MATCH(SMALL(IF('🗄️ Transactions'!$Y$5:$Y$200="Active",IF('🗄️ Transactions'!$H$5:$H$200>=TODAY()-1,'🗄️ Transactions'!$H$5:$H$200,9999999)),10),'🗄️ Transactions'!$H$5:$H$200,0)),"—") | D23: =IFERROR(SMALL(IF('🗄️ Transactions'!$Y$5:$Y$200="Active",IF('🗄️ Transactions'!$H$5:$H$200>=TODAY()-1,'🗄️ Transactions'!$H$5:$H$200,9999999)),10),"—") | E23: =IFERROR(D23-TODAY(),"—")
B25: 🚨 EARNEST MONEY NOT RECEIVED (EM Holder = HH, but EM Amount > 0)
B26: Txn ID | C26: Address | D26: EM Amount | E26: Closing Date
B27: =IFERROR(INDEX('🗄️ Transactions'!$A$5:$A$200,SMALL(IF(('🗄️ Transactions'!$Q$5:$Q$200="HH")*('🗄️ Transactions'!$P$5:$P$200>0)*('🗄️ Transactions'!$Y$5:$Y$200="Active"),ROW('🗄️ Transactions'!$A$5:$A$200)-ROW('🗄️ Transactions'!$A$5)+1),1)),"—") | C27: =IFERROR(INDEX('🗄️ Transactions'!$C$5:$C$200,SMALL(IF(('🗄️ Transactions'!$Q$5:$Q$200="HH")*('🗄️ Transactions'!$P$5:$P$200>0)*('🗄️ Transactions'!$Y$5:$Y$200="Active"),ROW('🗄️ Transactions'!$A$5:$A$200)-ROW('🗄️ Transactions'!$A$5)+1),1)),"—") | D27: =IFERROR(INDEX('🗄️ Transactions'!$P$5:$P$200,SMALL(IF(('🗄️ Transactions'!$Q$5:$Q$200="HH")*('🗄️ Transactions'!$P$5:$P$200>0)*('🗄️ Transactions'!$Y$5:$Y$200="Active"),ROW('🗄️ Transactions'!$A$5:$A$200)-ROW('🗄️ Transactions'!$A$5)+1),1)),"—") | E27: =IFERROR(INDEX('🗄️ Transactions'!$H$5:$H$200,SMALL(IF(('🗄️ Transactions'!$Q$5:$Q$200="HH")*('🗄️ Transactions'!$P$5:$P$200>0)*('🗄️ Transactions'!$Y$5:$Y$200="Active"),ROW('🗄️ Transactions'!$A$5:$A$200)-ROW('🗄️ Transactions'!$A$5)+1),1)),"—")
B28: =IFERROR(INDEX('🗄️ Transactions'!$A$5:$A$200,SMALL(IF(('🗄️ Transactions'!$Q$5:$Q$200="HH")*('🗄️ Transactions'!$P$5:$P$200>0)*('🗄️ Transactions'!$Y$5:$Y$200="Active"),ROW('🗄️ Transactions'!$A$5:$A$200)-ROW('🗄️ Transactions'!$A$5)+1),2)),"—") | C28: =IFERROR(INDEX('🗄️ Transactions'!$C$5:$C$200,SMALL(IF(('🗄️ Transactions'!$Q$5:$Q$200="HH")*('🗄️ Transactions'!$P$5:$P$200>0)*('🗄️ Transactions'!$Y$5:$Y$200="Active"),ROW('🗄️ Transactions'!$A$5:$A$200)-ROW('🗄️ Transactions'!$A$5)+1),2)),"—") | D28: =IFERROR(INDEX('🗄️ Transactions'!$P$5:$P$200,SMALL(IF(('🗄️ Transactions'!$Q$5:$Q$200="HH")*('🗄️ Transactions'!$P$5:$P$200>0)*('🗄️ Transactions'!$Y$5:$Y$200="Active"),ROW('🗄️ Transactions'!$A$5:$A$200)-ROW('🗄️ Transactions'!$A$5)+1),2)),"—") | E28: =IFERROR(INDEX('🗄️ Transactions'!$H$5:$H$200,SMALL(IF(('🗄️ Transactions'!$Q$5:$Q$200="HH")*('🗄️ Transactions'!$P$5:$P$200>0)*('🗄️ Transactions'!$Y$5:$Y$200="Active"),ROW('🗄️ Transactions'!$A$5:$A$200)-ROW('🗄️ Transactions'!$A$5)+1),2)),"—")
B29: =IFERROR(INDEX('🗄️ Transactions'!$A$5:$A$200,SMALL(IF(('🗄️ Transactions'!$Q$5:$Q$200="HH")*('🗄️ Transactions'!$P$5:$P$200>0)*('🗄️ Transactions'!$Y$5:$Y$200="Active"),ROW('🗄️ Transactions'!$A$5:$A$200)-ROW('🗄️ Transactions'!$A$5)+1),3)),"—") | C29: =IFERROR(INDEX('🗄️ Transactions'!$C$5:$C$200,SMALL(IF(('🗄️ Transactions'!$Q$5:$Q$200="HH")*('🗄️ Transactions'!$P$5:$P$200>0)*('🗄️ Transactions'!$Y$5:$Y$200="Active"),ROW('🗄️ Transactions'!$A$5:$A$200)-ROW('🗄️ Transactions'!$A$5)+1),3)),"—") | D29: =IFERROR(INDEX('🗄️ Transactions'!$P$5:$P$200,SMALL(IF(('🗄️ Transactions'!$Q$5:$Q$200="HH")*('🗄️ Transactions'!$P$5:$P$200>0)*('🗄️ Transactions'!$Y$5:$Y$200="Active"),ROW('🗄️ Transactions'!$A$5:$A$200)-ROW('🗄️ Transactions'!$A$5)+1),3)),"—") | E29: =IFERROR(INDEX('🗄️ Transactions'!$H$5:$H$200,SMALL(IF(('🗄️ Transactions'!$Q$5:$Q$200="HH")*('🗄️ Transactions'!$P$5:$P$200>0)*('🗄️ Transactions'!$Y$5:$Y$200="Active"),ROW('🗄️ Transactions'!$A$5:$A$200)-ROW('🗄️ Transactions'!$A$5)+1),3)),"—")
B30: =IFERROR(INDEX('🗄️ Transactions'!$A$5:$A$200,SMALL(IF(('🗄️ Transactions'!$Q$5:$Q$200="HH")*('🗄️ Transactions'!$P$5:$P$200>0)*('🗄️ Transactions'!$Y$5:$Y$200="Active"),ROW('🗄️ Transactions'!$A$5:$A$200)-ROW('🗄️ Transactions'!$A$5)+1),4)),"—") | C30: =IFERROR(INDEX('🗄️ Transactions'!$C$5:$C$200,SMALL(IF(('🗄️ Transactions'!$Q$5:$Q$200="HH")*('🗄️ Transactions'!$P$5:$P$200>0)*('🗄️ Transactions'!$Y$5:$Y$200="Active"),ROW('🗄️ Transactions'!$A$5:$A$200)-ROW('🗄️ Transactions'!$A$5)+1),4)),"—") | D30: =IFERROR(INDEX('🗄️ Transactions'!$P$5:$P$200,SMALL(IF(('🗄️ Transactions'!$Q$5:$Q$200="HH")*('🗄️ Transactions'!$P$5:$P$200>0)*('🗄️ Transactions'!$Y$5:$Y$200="Active"),ROW('🗄️ Transactions'!$A$5:$A$200)-ROW('🗄️ Transactions'!$A$5)+1),4)),"—") | E30: =IFERROR(INDEX('🗄️ Transactions'!$H$5:$H$200,SMALL(IF(('🗄️ Transactions'!$Q$5:$Q$200="HH")*('🗄️ Transactions'!$P$5:$P$200>0)*('🗄️ Transactions'!$Y$5:$Y$200="Active"),ROW('🗄️ Transactions'!$A$5:$A$200)-ROW('🗄️ Transactions'!$A$5)+1),4)),"—")
B31: =IFERROR(INDEX('🗄️ Transactions'!$A$5:$A$200,SMALL(IF(('🗄️ Transactions'!$Q$5:$Q$200="HH")*('🗄️ Transactions'!$P$5:$P$200>0)*('🗄️ Transactions'!$Y$5:$Y$200="Active"),ROW('🗄️ Transactions'!$A$5:$A$200)-ROW('🗄️ Transactions'!$A$5)+1),5)),"—") | C31: =IFERROR(INDEX('🗄️ Transactions'!$C$5:$C$200,SMALL(IF(('🗄️ Transactions'!$Q$5:$Q$200="HH")*('🗄️ Transactions'!$P$5:$P$200>0)*('🗄️ Transactions'!$Y$5:$Y$200="Active"),ROW('🗄️ Transactions'!$A$5:$A$200)-ROW('🗄️ Transactions'!$A$5)+1),5)),"—") | D31: =IFERROR(INDEX('🗄️ Transactions'!$P$5:$P$200,SMALL(IF(('🗄️ Transactions'!$Q$5:$Q$200="HH")*('🗄️ Transactions'!$P$5:$P$200>0)*('🗄️ Transactions'!$Y$5:$Y$200="Active"),ROW('🗄️ Transactions'!$A$5:$A$200)-ROW('🗄️ Transactions'!$A$5)+1),5)),"—") | E31: =IFERROR(INDEX('🗄️ Transactions'!$H$5:$H$200,SMALL(IF(('🗄️ Transactions'!$Q$5:$Q$200="HH")*('🗄️ Transactions'!$P$5:$P$200>0)*('🗄️ Transactions'!$Y$5:$Y$200="Active"),ROW('🗄️ Transactions'!$A$5:$A$200)-ROW('🗄️ Transactions'!$A$5)+1),5)),"—")
B32: =IFERROR(INDEX('🗄️ Transactions'!$A$5:$A$200,SMALL(IF(('🗄️ Transactions'!$Q$5:$Q$200="HH")*('🗄️ Transactions'!$P$5:$P$200>0)*('🗄️ Transactions'!$Y$5:$Y$200="Active"),ROW('🗄️ Transactions'!$A$5:$A$200)-ROW('🗄️ Transactions'!$A$5)+1),6)),"—") | C32: =IFERROR(INDEX('🗄️ Transactions'!$C$5:$C$200,SMALL(IF(('🗄️ Transactions'!$Q$5:$Q$200="HH")*('🗄️ Transactions'!$P$5:$P$200>0)*('🗄️ Transactions'!$Y$5:$Y$200="Active"),ROW('🗄️ Transactions'!$A$5:$A$200)-ROW('🗄️ Transactions'!$A$5)+1),6)),"—") | D32: =IFERROR(INDEX('🗄️ Transactions'!$P$5:$P$200,SMALL(IF(('🗄️ Transactions'!$Q$5:$Q$200="HH")*('🗄️ Transactions'!$P$5:$P$200>0)*('🗄️ Transactions'!$Y$5:$Y$200="Active"),ROW('🗄️ Transactions'!$A$5:$A$200)-ROW('🗄️ Transactions'!$A$5)+1),6)),"—") | E32: =IFERROR(INDEX('🗄️ Transactions'!$H$5:$H$200,SMALL(IF(('🗄️ Transactions'!$Q$5:$Q$200="HH")*('🗄️ Transactions'!$P$5:$P$200>0)*('🗄️ Transactions'!$Y$5:$Y$200="Active"),ROW('🗄️ Transactions'!$A$5:$A$200)-ROW('🗄️ Transactions'!$A$5)+1),6)),"—")
B33: =IFERROR(INDEX('🗄️ Transactions'!$A$5:$A$200,SMALL(IF(('🗄️ Transactions'!$Q$5:$Q$200="HH")*('🗄️ Transactions'!$P$5:$P$200>0)*('🗄️ Transactions'!$Y$5:$Y$200="Active"),ROW('🗄️ Transactions'!$A$5:$A$200)-ROW('🗄️ Transactions'!$A$5)+1),7)),"—") | C33: =IFERROR(INDEX('🗄️ Transactions'!$C$5:$C$200,SMALL(IF(('🗄️ Transactions'!$Q$5:$Q$200="HH")*('🗄️ Transactions'!$P$5:$P$200>0)*('🗄️ Transactions'!$Y$5:$Y$200="Active"),ROW('🗄️ Transactions'!$A$5:$A$200)-ROW('🗄️ Transactions'!$A$5)+1),7)),"—") | D33: =IFERROR(INDEX('🗄️ Transactions'!$P$5:$P$200,SMALL(IF(('🗄️ Transactions'!$Q$5:$Q$200="HH")*('🗄️ Transactions'!$P$5:$P$200>0)*('🗄️ Transactions'!$Y$5:$Y$200="Active"),ROW('🗄️ Transactions'!$A$5:$A$200)-ROW('🗄️ Transactions'!$A$5)+1),7)),"—") | E33: =IFERROR(INDEX('🗄️ Transactions'!$H$5:$H$200,SMALL(IF(('🗄️ Transactions'!$Q$5:$Q$200="HH")*('🗄️ Transactions'!$P$5:$P$200>0)*('🗄️ Transactions'!$Y$5:$Y$200="Active"),ROW('🗄️ Transactions'!$A$5:$A$200)-ROW('🗄️ Transactions'!$A$5)+1),7)),"—")
B34: =IFERROR(INDEX('🗄️ Transactions'!$A$5:$A$200,SMALL(IF(('🗄️ Transactions'!$Q$5:$Q$200="HH")*('🗄️ Transactions'!$P$5:$P$200>0)*('🗄️ Transactions'!$Y$5:$Y$200="Active"),ROW('🗄️ Transactions'!$A$5:$A$200)-ROW('🗄️ Transactions'!$A$5)+1),8)),"—") | C34: =IFERROR(INDEX('🗄️ Transactions'!$C$5:$C$200,SMALL(IF(('🗄️ Transactions'!$Q$5:$Q$200="HH")*('🗄️ Transactions'!$P$5:$P$200>0)*('🗄️ Transactions'!$Y$5:$Y$200="Active"),ROW('🗄️ Transactions'!$A$5:$A$200)-ROW('🗄️ Transactions'!$A$5)+1),8)),"—") | D34: =IFERROR(INDEX('🗄️ Transactions'!$P$5:$P$200,SMALL(IF(('🗄️ Transactions'!$Q$5:$Q$200="HH")*('🗄️ Transactions'!$P$5:$P$200>0)*('🗄️ Transactions'!$Y$5:$Y$200="Active"),ROW('🗄️ Transactions'!$A$5:$A$200)-ROW('🗄️ Transactions'!$A$5)+1),8)),"—") | E34: =IFERROR(INDEX('🗄️ Transactions'!$H$5:$H$200,SMALL(IF(('🗄️ Transactions'!$Q$5:$Q$200="HH")*('🗄️ Transactions'!$P$5:$P$200>0)*('🗄️ Transactions'!$Y$5:$Y$200="Active"),ROW('🗄️ Transactions'!$A$5:$A$200)-ROW('🗄️ Transactions'!$A$5)+1),8)),"—")
B36: 💼 HH REVENUE SUMMARY (Active Transactions)
B37: Metric | C37: Amount | D37: Count | E37: Avg/Transaction
B38: Total HH Revenue (Active) | C38: =SUMIF('🗄️ Transactions'!Y5:Y200,"Active",'🗄️ Transactions'!AI5:AI200) | D38: =COUNTIF('🗄️ Transactions'!Y5:Y200,"Active") | E38: =IFERROR(C38/D38,"—")
B39: Total Commission Generated | C39: =SUMIF('🗄️ Transactions'!Y5:Y200,"Active",'🗄️ Transactions'!AE5:AE200) | D39: =COUNTIF('🗄️ Transactions'!Y5:Y200,"Active") | E39: =IFERROR(C39/D39,"—")
B40: Total Sale Value (Active) | C40: =SUMIF('🗄️ Transactions'!Y5:Y200,"Active",'🗄️ Transactions'!F5:F200) | D40: =COUNTIF('🗄️ Transactions'!Y5:Y200,"Active") | E40: =IFERROR(C40/D40,"—")
B41: HH Listing Revenue | C41: =SUMPRODUCT(('🗄️ Transactions'!Y5:Y200="Active")*('🗄️ Transactions'!AB5:AB200="Yes"),'🗄️ Transactions'!AG5:AG200) | D41: =COUNTIFS('🗄️ Transactions'!Y5:Y200,"Active",'🗄️ Transactions'!AB5:AB200,"Yes") | E41: =IFERROR(C41/D41,"—")
B42: HH Sale Revenue | C42: =SUMPRODUCT(('🗄️ Transactions'!Y5:Y200="Active")*('🗄️ Transactions'!AC5:AC200="Yes"),'🗄️ Transactions'!AH5:AH200) | D42: =COUNTIFS('🗄️ Transactions'!Y5:Y200,"Active",'🗄️ Transactions'!AC5:AC200,"Yes") | E42: =IFERROR(C42/D42,"—")
B43: Flat Fee Revenue | C43: =SUMPRODUCT(('🗄️ Transactions'!Y5:Y200="Active")*('🗄️ Transactions'!U5:U200="Yes"),'🗄️ Transactions'!AF5:AF200) | D43: =COUNTIFS('🗄️ Transactions'!Y5:Y200,"Active",'🗄️ Transactions'!U5:U200,"Yes") | E43: =IFERROR(C43/D43,"—")

Sheet 🏠 Input Form
A1: 🏠 NEW TRANSACTION ENTRY FORM — Fill in the yellow fields, then add to Transactions sheet
A2: ★ = Required field | Fill ALL starred fields before saving | Blue cells = auto-filled, do not edit
B4: 📋 SYSTEM INFORMATION (auto-filled, do not edit)
B5: Transaction ID | C5: =TEXT(YEAR(TODAY()),"0000")&"-"&TEXT(COUNTA('🗄️ Transactions'!A:A)-3,"000") | E5: Entry Date | F5: =TODAY()
B7: 🏠 PROPERTY INFORMATION
B8: ★ Address (Street, City Zip) | E8: ★ Closing Date
B9: ★ List Price ($) | E9: Sale Price ($)
B10: Offer Accepted Date | E10: Sign # (if our listing)
B11: ★ Loan Type (dropdown ↓) | E11: Concessions ($)
B13: 👤 AGENT & COMMISSION
B14: ★ List Agent (dropdown ↓) | E14: ★ Sell Agent (dropdown ↓)
B15: Total Comm % (e.g. 0.06) | E15: Listing Side % (e.g. 0.03)
B16: Flat Comm Amount (if flat fee) | E16: Flat Fee Add-On?
B19: 💰 EARNEST MONEY & HOME WARRANTY
B20: Earnest Money Amount ($) | E20: EM Holder (dropdown ↓)
B21: Home Warranty? (Yes/No) | E21: HW Payer (dropdown ↓)
B22: HSA? (Yes/No) | E22: Title Company
B25: 📝 ADDITIONAL NOTES
B28: 📌 HOW TO ADD THIS TRANSACTION
B29: 1. Fill in all yellow cells above (★ = required). 2. Go to the '🗄️ Transactions' sheet. 3. Scroll to the first EMPTY row at the bottom. 4. Copy each value from this form into the matching column. 5. Return here and press Ctrl+Z multiple times to clear the form for next use, OR simply type over the values with the next transaction's information.

Sheet 🗄️ Transactions
A1: 🗄️ HH REALTY — TRANSACTION REGISTER · All active, closed and BOMB transactions
A2: 🟡 YELLOW = Type here 🔵 BLUE = Auto-calculated (do not edit) ⚪ GREY = Locked system field | Z2: ◀ CALCULATED COLUMNS — Do Not Edit
A3: SYSTEM | C3: ◀ INPUT FIELDS — Type in the yellow cells ▶ | Z3: ◀ AUTO-CALCULATED — Do not edit ▶
A4: Txn ID | B4: Created | C4: ★ Address | D4: Sign # | E4: List Price | F4: Sale Price | G4: Offer Accepted | H4: ★ Closing Date | I4: ★ Loan Type | J4: Concessions ($) | K4: ★ List Agent | L4: ★ Sell Agent | M4: Comm % | N4: List Side % | O4: Flat $ Amount | P4: EM Amount | Q4: EM Holder | R4: Home Warranty | S4: HSA | T4: HW Payer | U4: Flat Fee? | V4: Title Co. | W4: Title Contact | X4: Notes | Y4: Status | Z4: List Office | AA4: Sell Office | AB4: HH Listing? | AC4: HH Sale? | AD4: Sale Comm % | AE4: Total Comm | AF4: Flat Fee Amt | AG4: Listing Side | AH4: Sale Side | AI4: HH Revenue | AJ4: Comm Check
A5: 2026-001 | B5: 46079 | C5: 998 Barn Swallow, Wadsworth 44281 | F5: 617785 | H5: 46096 | I5: New Const | J5: 0 | K5: Pulte Homes | L5: Kelly Watts | M5: 0.02 | N5: 0 | U5: Yes | Y5: Active | Z5: =IFERROR(VLOOKUP(K5,'👤 Agents'!$C$4:$D$200,2,FALSE),"") | AA5: =IFERROR(VLOOKUP(L5,'👤 Agents'!$C$4:$D$200,2,FALSE),"") | AB5: =IF(Z5="HH","Yes","No") | AC5: =IF(AA5="HH","Yes","No") | AD5: =IFERROR(IF(M5>0,M5-N5,0),0) | AE5: =IFERROR(IF(M5>0,F5*M5,IF(O5>0,O5,0)),0) | AF5: =IF(U5="Yes",399,0) | AG5: =IFERROR(IF(N5>0,F5*N5,IF(AND(AB5="Yes",O5>0),O5/2,0)),0) | AH5: =IFERROR(IF(AD5>0,F5*AD5,IF(AND(AC5="Yes",O5>0),O5/2,0)),0) | AI5: =IF(AB5="Yes",AG5,0)+IF(AC5="Yes",AH5,0)+AF5 | AJ5: =IF(AE5=0,"",IF(ABS(AE5-(AG5+AH5))<1,"✓ OK","⚠️ CHECK: Total="&TEXT(AE5,"$#,##0")&" vs Sides="&TEXT(AG5+AH5,"$#,##0")))
A6: 2026-002 | B6: 46079 | C6: 133 Beck, Wadsworth 44281 | F6: 85500 | H6: 46087 | I6: CASH | J6: 0 | K6: Barb Lesure | L6: Ron Ho | M6: 0 | N6: 0 | O6: 2500 | U6: No | Y6: Active | Z6: =IFERROR(VLOOKUP(K6,'👤 Agents'!$C$4:$D$200,2,FALSE),"") | AA6: =IFERROR(VLOOKUP(L6,'👤 Agents'!$C$4:$D$200,2,FALSE),"") | AB6: =IF(Z6="HH","Yes","No") | AC6: =IF(AA6="HH","Yes","No") | AD6: =IFERROR(IF(M6>0,M6-N6,0),0) | AE6: =IFERROR(IF(M6>0,F6*M6,IF(O6>0,O6,0)),0) | AF6: =IF(U6="Yes",399,0) | AG6: =IFERROR(IF(N6>0,F6*N6,IF(AND(AB6="Yes",O6>0),O6/2,0)),0) | AH6: =IFERROR(IF(AD6>0,F6*AD6,IF(AND(AC6="Yes",O6>0),O6/2,0)),0) | AI6: =IF(AB6="Yes",AG6,0)+IF(AC6="Yes",AH6,0)+AF6 | AJ6: =IF(AE6=0,"",IF(ABS(AE6-(AG6+AH6))<1,"✓ OK","⚠️ CHECK: Total="&TEXT(AE6,"$#,##0")&" vs Sides="&TEXT(AG6+AH6,"$#,##0")))
A7: 2026-003 | B7: 46079 | C7: 743 Bent Creek, Wadsworth 44281 | F7: 245000 | H7: 46088 | I7: CASH | J7: 0 | K7: Ivana Carson | L7: Amy Frary | M7: 0.02 | N7: 0 | U7: Yes | Y7: Active | Z7: =IFERROR(VLOOKUP(K7,'👤 Agents'!$C$4:$D$200,2,FALSE),"") | AA7: =IFERROR(VLOOKUP(L7,'👤 Agents'!$C$4:$D$200,2,FALSE),"") | AB7: =IF(Z7="HH","Yes","No") | AC7: =IF(AA7="HH","Yes","No") | AD7: =IFERROR(IF(M7>0,M7-N7,0),0) | AE7: =IFERROR(IF(M7>0,F7*M7,IF(O7>0,O7,0)),0) | AF7: =IF(U7="Yes",399,0) | AG7: =IFERROR(IF(N7>0,F7*N7,IF(AND(AB7="Yes",O7>0),O7/2,0)),0) | AH7: =IFERROR(IF(AD7>0,F7*AD7,IF(AND(AC7="Yes",O7>0),O7/2,0)),0) | AI7: =IF(AB7="Yes",AG7,0)+IF(AC7="Yes",AH7,0)+AF7 | AJ7: =IF(AE7=0,"",IF(ABS(AE7-(AG7+AH7))<1,"✓ OK","⚠️ CHECK: Total="&TEXT(AE7,"$#,##0")&" vs Sides="&TEXT(AG7+AH7,"$#,##0")))
A8: 2026-004 | B8: 46079 | C8: 2644 Harpster, Rittman 44270 | F8: 275000 | H8: 46094 | I8: FHA | J8: 0 | K8: Karen/Milka | L8: Jerry Lesac | M8: 0.06 | N8: 0.03 | U8: Yes | Y8: Active | Z8: =IFERROR(VLOOKUP(K8,'👤 Agents'!$C$4:$D$200,2,FALSE),"") | AA8: =IFERROR(VLOOKUP(L8,'👤 Agents'!$C$4:$D$200,2,FALSE),"") | AB8: =IF(Z8="HH","Yes","No") | AC8: =IF(AA8="HH","Yes","No") | AD8: =IFERROR(IF(M8>0,M8-N8,0),0) | AE8: =IFERROR(IF(M8>0,F8*M8,IF(O8>0,O8,0)),0) | AF8: =IF(U8="Yes",399,0) | AG8: =IFERROR(IF(N8>0,F8*N8,IF(AND(AB8="Yes",O8>0),O8/2,0)),0) | AH8: =IFERROR(IF(AD8>0,F8*AD8,IF(AND(AC8="Yes",O8>0),O8/2,0)),0) | AI8: =IF(AB8="Yes",AG8,0)+IF(AC8="Yes",AH8,0)+AF8 | AJ8: =IF(AE8=0,"",IF(ABS(AE8-(AG8+AH8))<1,"✓ OK","⚠️ CHECK: Total="&TEXT(AE8,"$#,##0")&" vs Sides="&TEXT(AG8+AH8,"$#,##0")))
A9: 2026-005 | B9: 46079 | C9: 1774 Hila Way, Wooster 44691 | F9: 310000 | H9: 46080 | I9: CONV | J9: 600 | K9: Kelly/Heidi | L9: Cindy McCory | M9: 0.055 | N9: 0.03 | U9: Yes | Y9: Active | Z9: =IFERROR(VLOOKUP(K9,'👤 Agents'!$C$4:$D$200,2,FALSE),"") | AA9: =IFERROR(VLOOKUP(L9,'👤 Agents'!$C$4:$D$200,2,FALSE),"") | AB9: =IF(Z9="HH","Yes","No") | AC9: =IF(AA9="HH","Yes","No") | AD9: =IFERROR(IF(M9>0,M9-N9,0),0) | AE9: =IFERROR(IF(M9>0,F9*M9,IF(O9>0,O9,0)),0) | AF9: =IF(U9="Yes",399,0) | AG9: =IFERROR(IF(N9>0,F9*N9,IF(AND(AB9="Yes",O9>0),O9/2,0)),0) | AH9: =IFERROR(IF(AD9>0,F9*AD9,IF(AND(AC9="Yes",O9>0),O9/2,0)),0) | AI9: =IF(AB9="Yes",AG9,0)+IF(AC9="Yes",AH9,0)+AF9 | AJ9: =IF(AE9=0,"",IF(ABS(AE9-(AG9+AH9))<1,"✓ OK","⚠️ CHECK: Total="&TEXT(AE9,"$#,##0")&" vs Sides="&TEXT(AG9+AH9,"$#,##0")))
A10: 2026-006 | B10: 46079 | C10: 744 Lawrence, Wadsworth 44281 | F10: 360000 | H10: 46069 | I10: CONV | J10: 0 | K10: Matthew Kalogeras | L10: Rachel Eastwood | M10: 0.03 | N10: 0 | P10: 1000 | U10: Yes | Y10: Active | Z10: =IFERROR(VLOOKUP(K10,'👤 Agents'!$C$4:$D$200,2,FALSE),"") | AA10: =IFERROR(VLOOKUP(L10,'👤 Agents'!$C$4:$D$200,2,FALSE),"") | AB10: =IF(Z10="HH","Yes","No") | AC10: =IF(AA10="HH","Yes","No") | AD10: =IFERROR(IF(M10>0,M10-N10,0),0) | AE10: =IFERROR(IF(M10>0,F10*M10,IF(O10>0,O10,0)),0) | AF10: =IF(U10="Yes",399,0) | AG10: =IFERROR(IF(N10>0,F10*N10,IF(AND(AB10="Yes",O10>0),O10/2,0)),0) | AH10: =IFERROR(IF(AD10>0,F10*AD10,IF(AND(AC10="Yes",O10>0),O10/2,0)),0) | AI10: =IF(AB10="Yes",AG10,0)+IF(AC10="Yes",AH10,0)+AF10 | AJ10: =IF(AE10=0,"",IF(ABS(AE10-(AG10+AH10))<1,"✓ OK","⚠️ CHECK: Total="&TEXT(AE10,"$#,##0")&" vs Sides="&TEXT(AG10+AH10,"$#,##0")))
A11: 2026-007 | B11: 46079 | C11: 281 Park Pl, Wadsworth 44281 | F11: 266000 | H11: 46086 | I11: Eq. Ln | J11: 0 | K11: Mark Metz | L11: Karen/Milka | M11: 0.03 | N11: 0 | P11: 2000 | U11: Yes | Y11: Active | Z11: =IFERROR(VLOOKUP(K11,'👤 Agents'!$C$4:$D$200,2,FALSE),"") | AA11: =IFERROR(VLOOKUP(L11,'👤 Agents'!$C$4:$D$200,2,FALSE),"") | AB11: =IF(Z11="HH","Yes","No") | AC11: =IF(AA11="HH","Yes","No") | AD11: =IFERROR(IF(M11>0,M11-N11,0),0) | AE11: =IFERROR(IF(M11>0,F11*M11,IF(O11>0,O11,0)),0) | AF11: =IF(U11="Yes",399,0) | AG11: =IFERROR(IF(N11>0,F11*N11,IF(AND(AB11="Yes",O11>0),O11/2,0)),0) | AH11: =IFERROR(IF(AD11>0,F11*AD11,IF(AND(AC11="Yes",O11>0),O11/2,0)),0) | AI11: =IF(AB11="Yes",AG11,0)+IF(AC11="Yes",AH11,0)+AF11 | AJ11: =IF(AE11=0,"",IF(ABS(AE11-(AG11+AH11))<1,"✓ OK","⚠️ CHECK: Total="&TEXT(AE11,"$#,##0")&" vs Sides="&TEXT(AG11+AH11,"$#,##0")))
A12: 2026-008 | B12: 46079 | C12: 92 30th, Barberton 44203 | F12: 193000 | H12: 46080 | I12: CONV | J12: 0 | K12: Eric Yetzer | L12: Mark Metz | M12: 0.065 | N12: 0.035 | U12: Yes | Y12: Active | Z12: =IFERROR(VLOOKUP(K12,'👤 Agents'!$C$4:$D$200,2,FALSE),"") | AA12: =IFERROR(VLOOKUP(L12,'👤 Agents'!$C$4:$D$200,2,FALSE),"") | AB12: =IF(Z12="HH","Yes","No") | AC12: =IF(AA12="HH","Yes","No") | AD12: =IFERROR(IF(M12>0,M12-N12,0),0) | AE12: =IFERROR(IF(M12>0,F12*M12,IF(O12>0,O12,0)),0) | AF12: =IF(U12="Yes",399,0) | AG12: =IFERROR(IF(N12>0,F12*N12,IF(AND(AB12="Yes",O12>0),O12/2,0)),0) | AH12: =IFERROR(IF(AD12>0,F12*AD12,IF(AND(AC12="Yes",O12>0),O12/2,0)),0) | AI12: =IF(AB12="Yes",AG12,0)+IF(AC12="Yes",AH12,0)+AF12 | AJ12: =IF(AE12=0,"",IF(ABS(AE12-(AG12+AH12))<1,"✓ OK","⚠️ CHECK: Total="&TEXT(AE12,"$#,##0")&" vs Sides="&TEXT(AG12+AH12,"$#,##0")))
A13: 2026-009 | B13: 46079 | C13: 455 Barrenwood, Wadsworth 44281 | F13: 315000 | H13: 46092 | I13: CASH | J13: 6300 | K13: Rebbecca Tessanne | L13: Oleg Bosovic | M13: 0.046 | N13: 0.026 | U13: Yes | Y13: Active | Z13: =IFERROR(VLOOKUP(K13,'👤 Agents'!$C$4:$D$200,2,FALSE),"") | AA13: =IFERROR(VLOOKUP(L13,'👤 Agents'!$C$4:$D$200,2,FALSE),"") | AB13: =IF(Z13="HH","Yes","No") | AC13: =IF(AA13="HH","Yes","No") | AD13: =IFERROR(IF(M13>0,M13-N13,0),0) | AE13: =IFERROR(IF(M13>0,F13*M13,IF(O13>0,O13,0)),0) | AF13: =IF(U13="Yes",399,0) | AG13: =IFERROR(IF(N13>0,F13*N13,IF(AND(AB13="Yes",O13>0),O13/2,0)),0) | AH13: =IFERROR(IF(AD13>0,F13*AD13,IF(AND(AC13="Yes",O13>0),O13/2,0)),0) | AI13: =IF(AB13="Yes",AG13,0)+IF(AC13="Yes",AH13,0)+AF13 | AJ13: =IF(AE13=0,"",IF(ABS(AE13-(AG13+AH13))<1,"✓ OK","⚠️ CHECK: Total="&TEXT(AE13,"$#,##0")&" vs Sides="&TEXT(AG13+AH13,"$#,##0")))
A14: 2026-010 | B14: 46079 | C14: 5052 Catawba, Seville 44273 | F14: 365000 | H14: 46119 | I14: CONV | J14: 0 | K14: Eric Yetzer | L14: Shelly Booth | M14: 0.06 | N14: 0.03 | U14: No | Y14: Active | Z14: =IFERROR(VLOOKUP(K14,'👤 Agents'!$C$4:$D$200,2,FALSE),"") | AA14: =IFERROR(VLOOKUP(L14,'👤 Agents'!$C$4:$D$200,2,FALSE),"") | AB14: =IF(Z14="HH","Yes","No") | AC14: =IF(AA14="HH","Yes","No") | AD14: =IFERROR(IF(M14>0,M14-N14,0),0) | AE14: =IFERROR(IF(M14>0,F14*M14,IF(O14>0,O14,0)),0) | AF14: =IF(U14="Yes",399,0) | AG14: =IFERROR(IF(N14>0,F14*N14,IF(AND(AB14="Yes",O14>0),O14/2,0)),0) | AH14: =IFERROR(IF(AD14>0,F14*AD14,IF(AND(AC14="Yes",O14>0),O14/2,0)),0) | AI14: =IF(AB14="Yes",AG14,0)+IF(AC14="Yes",AH14,0)+AF14 | AJ14: =IF(AE14=0,"",IF(ABS(AE14-(AG14+AH14))<1,"✓ OK","⚠️ CHECK: Total="&TEXT(AE14,"$#,##0")&" vs Sides="&TEXT(AG14+AH14,"$#,##0")))
A15: 2026-011 | B15: 46079 | C15: 216 N. Lyman, Wadsworth 44281 | F15: 235000 | H15: 46087 | I15: FHA | J15: 5000 | K15: Ron Ho | L15: Autumn Moore | M15: 0.06 | N15: 0 | U15: Yes | Y15: Active | Z15: =IFERROR(VLOOKUP(K15,'👤 Agents'!$C$4:$D$200,2,FALSE),"") | AA15: =IFERROR(VLOOKUP(L15,'👤 Agents'!$C$4:$D$200,2,FALSE),"") | AB15: =IF(Z15="HH","Yes","No") | AC15: =IF(AA15="HH","Yes","No") | AD15: =IFERROR(IF(M15>0,M15-N15,0),0) | AE15: =IFERROR(IF(M15>0,F15*M15,IF(O15>0,O15,0)),0) | AF15: =IF(U15="Yes",399,0) | AG15: =IFERROR(IF(N15>0,F15*N15,IF(AND(AB15="Yes",O15>0),O15/2,0)),0) | AH15: =IFERROR(IF(AD15>0,F15*AD15,IF(AND(AC15="Yes",O15>0),O15/2,0)),0) | AI15: =IF(AB15="Yes",AG15,0)+IF(AC15="Yes",AH15,0)+AF15 | AJ15: =IF(AE15=0,"",IF(ABS(AE15-(AG15+AH15))<1,"✓ OK","⚠️ CHECK: Total="&TEXT(AE15,"$#,##0")&" vs Sides="&TEXT(AG15+AH15,"$#,##0")))
A16: 2026-012 | B16: 46079 | C16: 6407 Southview, Clinton 44216 | F16: 256000 | H16: 46097 | I16: CONV | J16: 0 | K16: Vicky & Beth | L16: Vicky & Beth | M16: 0.04 | N16: 0.025 | U16: Yes | Y16: Active | Z16: =IFERROR(VLOOKUP(K16,'👤 Agents'!$C$4:$D$200,2,FALSE),"") | AA16: =IFERROR(VLOOKUP(L16,'👤 Agents'!$C$4:$D$200,2,FALSE),"") | AB16: =IF(Z16="HH","Yes","No") | AC16: =IF(AA16="HH","Yes","No") | AD16: =IFERROR(IF(M16>0,M16-N16,0),0) | AE16: =IFERROR(IF(M16>0,F16*M16,IF(O16>0,O16,0)),0) | AF16: =IF(U16="Yes",399,0) | AG16: =IFERROR(IF(N16>0,F16*N16,IF(AND(AB16="Yes",O16>0),O16/2,0)),0) | AH16: =IFERROR(IF(AD16>0,F16*AD16,IF(AND(AC16="Yes",O16>0),O16/2,0)),0) | AI16: =IF(AB16="Yes",AG16,0)+IF(AC16="Yes",AH16,0)+AF16 | AJ16: =IF(AE16=0,"",IF(ABS(AE16-(AG16+AH16))<1,"✓ OK","⚠️ CHECK: Total="&TEXT(AE16,"$#,##0")&" vs Sides="&TEXT(AG16+AH16,"$#,##0")))
A17: 2026-013 | B17: 46079 | C17: 1821 Myersville, Akron 44312 | F17: 330000 | H17: 46079 | I17: FHA | J17: 9900 | K17: Lenny Herbert | L17: Vicky & Beth (Shelly) | M17: 0.02 | N17: 0 | P17: 1000 | U17: Yes | Y17: Active | Z17: =IFERROR(VLOOKUP(K17,'👤 Agents'!$C$4:$D$200,2,FALSE),"") | AA17: =IFERROR(VLOOKUP(L17,'👤 Agents'!$C$4:$D$200,2,FALSE),"") | AB17: =IF(Z17="HH","Yes","No") | AC17: =IF(AA17="HH","Yes","No") | AD17: =IFERROR(IF(M17>0,M17-N17,0),0) | AE17: =IFERROR(IF(M17>0,F17*M17,IF(O17>0,O17,0)),0) | AF17: =IF(U17="Yes",399,0) | AG17: =IFERROR(IF(N17>0,F17*N17,IF(AND(AB17="Yes",O17>0),O17/2,0)),0) | AH17: =IFERROR(IF(AD17>0,F17*AD17,IF(AND(AC17="Yes",O17>0),O17/2,0)),0) | AI17: =IF(AB17="Yes",AG17,0)+IF(AC17="Yes",AH17,0)+AF17 | AJ17: =IF(AE17=0,"",IF(ABS(AE17-(AG17+AH17))<1,"✓ OK","⚠️ CHECK: Total="&TEXT(AE17,"$#,##0")&" vs Sides="&TEXT(AG17+AH17,"$#,##0")))
A18: 2026-014 | B18: 46079 | C18: 96 W Ohio, Rittman 44270 | F18: 168000 | H18: 46094 | I18: CONV | J18: 2500 | K18: Eric Yetzer | L18: Brian Leatherman | M18: 0.065 | N18: 0.035 | U18: Yes | Y18: Active | Z18: =IFERROR(VLOOKUP(K18,'👤 Agents'!$C$4:$D$200,2,FALSE),"") | AA18: =IFERROR(VLOOKUP(L18,'👤 Agents'!$C$4:$D$200,2,FALSE),"") | AB18: =IF(Z18="HH","Yes","No") | AC18: =IF(AA18="HH","Yes","No") | AD18: =IFERROR(IF(M18>0,M18-N18,0),0) | AE18: =IFERROR(IF(M18>0,F18*M18,IF(O18>0,O18,0)),0) | AF18: =IF(U18="Yes",399,0) | AG18: =IFERROR(IF(N18>0,F18*N18,IF(AND(AB18="Yes",O18>0),O18/2,0)),0) | AH18: =IFERROR(IF(AD18>0,F18*AD18,IF(AND(AC18="Yes",O18>0),O18/2,0)),0) | AI18: =IF(AB18="Yes",AG18,0)+IF(AC18="Yes",AH18,0)+AF18 | AJ18: =IF(AE18=0,"",IF(ABS(AE18-(AG18+AH18))<1,"✓ OK","⚠️ CHECK: Total="&TEXT(AE18,"$#,##0")&" vs Sides="&TEXT(AG18+AH18,"$#,##0")))
A19: 2026-015 | B19: 46079 | C19: 317 Ihrig, Wooster 44691 | F19: 230000 | H19: 46101 | I19: CONV | J19: 6000 | K19: Vicky & Beth (Shelly) | L19: Cindy McCory | M19: 0.03 | N19: 0.01 | U19: Yes | Y19: Active | Z19: =IFERROR(VLOOKUP(K19,'👤 Agents'!$C$4:$D$200,2,FALSE),"") | AA19: =IFERROR(VLOOKUP(L19,'👤 Agents'!$C$4:$D$200,2,FALSE),"") | AB19: =IF(Z19="HH","Yes","No") | AC19: =IF(AA19="HH","Yes","No") | AD19: =IFERROR(IF(M19>0,M19-N19,0),0) | AE19: =IFERROR(IF(M19>0,F19*M19,IF(O19>0,O19,0)),0) | AF19: =IF(U19="Yes",399,0) | AG19: =IFERROR(IF(N19>0,F19*N19,IF(AND(AB19="Yes",O19>0),O19/2,0)),0) | AH19: =IFERROR(IF(AD19>0,F19*AD19,IF(AND(AC19="Yes",O19>0),O19/2,0)),0) | AI19: =IF(AB19="Yes",AG19,0)+IF(AC19="Yes",AH19,0)+AF19 | AJ19: =IF(AE19=0,"",IF(ABS(AE19-(AG19+AH19))<1,"✓ OK","⚠️ CHECK: Total="&TEXT(AE19,"$#,##0")&" vs Sides="&TEXT(AG19+AH19,"$#,##0")))
A20: 2026-016 | B20: 46079 | C20: 6116 Boneta, Medina 44256 | F20: 541000 | H20: 46085 | I20: CONV | J20: 0 | K20: Debbie Ferrante | L20: Eric Yetzer | M20: 0.02 | N20: 0 | P20: 3000 | U20: Yes | Y20: Active | Z20: =IFERROR(VLOOKUP(K20,'👤 Agents'!$C$4:$D$200,2,FALSE),"") | AA20: =IFERROR(VLOOKUP(L20,'👤 Agents'!$C$4:$D$200,2,FALSE),"") | AB20: =IF(Z20="HH","Yes","No") | AC20: =IF(AA20="HH","Yes","No") | AD20: =IFERROR(IF(M20>0,M20-N20,0),0) | AE20: =IFERROR(IF(M20>0,F20*M20,IF(O20>0,O20,0)),0) | AF20: =IF(U20="Yes",399,0) | AG20: =IFERROR(IF(N20>0,F20*N20,IF(AND(AB20="Yes",O20>0),O20/2,0)),0) | AH20: =IFERROR(IF(AD20>0,F20*AD20,IF(AND(AC20="Yes",O20>0),O20/2,0)),0) | AI20: =IF(AB20="Yes",AG20,0)+IF(AC20="Yes",AH20,0)+AF20 | AJ20: =IF(AE20=0,"",IF(ABS(AE20-(AG20+AH20))<1,"✓ OK","⚠️ CHECK: Total="&TEXT(AE20,"$#,##0")&" vs Sides="&TEXT(AG20+AH20,"$#,##0")))
A21: 2026-017 | B21: 46079 | C21: 2736 Applehill, Robertsville 44670 | F21: 67000 | H21: 46080 | I21: CASH | J21: 0 | K21: Vicky & Beth (Shelly) | L21: Lila Wohlwend | M21: 0.04 | N21: 0 | U21: Yes | Y21: Active | Z21: =IFERROR(VLOOKUP(K21,'👤 Agents'!$C$4:$D$200,2,FALSE),"") | AA21: =IFERROR(VLOOKUP(L21,'👤 Agents'!$C$4:$D$200,2,FALSE),"") | AB21: =IF(Z21="HH","Yes","No") | AC21: =IF(AA21="HH","Yes","No") | AD21: =IFERROR(IF(M21>0,M21-N21,0),0) | AE21: =IFERROR(IF(M21>0,F21*M21,IF(O21>0,O21,0)),0) | AF21: =IF(U21="Yes",399,0) | AG21: =IFERROR(IF(N21>0,F21*N21,IF(AND(AB21="Yes",O21>0),O21/2,0)),0) | AH21: =IFERROR(IF(AD21>0,F21*AD21,IF(AND(AC21="Yes",O21>0),O21/2,0)),0) | AI21: =IF(AB21="Yes",AG21,0)+IF(AC21="Yes",AH21,0)+AF21 | AJ21: =IF(AE21=0,"",IF(ABS(AE21-(AG21+AH21))<1,"✓ OK","⚠️ CHECK: Total="&TEXT(AE21,"$#,##0")&" vs Sides="&TEXT(AG21+AH21,"$#,##0")))
A22: 2026-018 | B22: 46079 | C22: 552 Main #H, Wadsworth 44281 | F22: 200000 | H22: 46093 | I22: CASH | J22: 0 | K22: Jennifer Ham | L22: Barb Lesure | M22: 0.025 | N22: 0 | P22: 1000 | U22: Yes | Y22: Active | Z22: =IFERROR(VLOOKUP(K22,'👤 Agents'!$C$4:$D$200,2,FALSE),"") | AA22: =IFERROR(VLOOKUP(L22,'👤 Agents'!$C$4:$D$200,2,FALSE),"") | AB22: =IF(Z22="HH","Yes","No") | AC22: =IF(AA22="HH","Yes","No") | AD22: =IFERROR(IF(M22>0,M22-N22,0),0) | AE22: =IFERROR(IF(M22>0,F22*M22,IF(O22>0,O22,0)),0) | AF22: =IF(U22="Yes",399,0) | AG22: =IFERROR(IF(N22>0,F22*N22,IF(AND(AB22="Yes",O22>0),O22/2,0)),0) | AH22: =IFERROR(IF(AD22>0,F22*AD22,IF(AND(AC22="Yes",O22>0),O22/2,0)),0) | AI22: =IF(AB22="Yes",AG22,0)+IF(AC22="Yes",AH22,0)+AF22 | AJ22: =IF(AE22=0,"",IF(ABS(AE22-(AG22+AH22))<1,"✓ OK","⚠️ CHECK: Total="&TEXT(AE22,"$#,##0")&" vs Sides="&TEXT(AG22+AH22,"$#,##0")))
A23: 2026-019 | B23: 46079 | C23: 1047 Ashwood, Wooster 44691 | E23: 335000 | F23: 325000 | G23: 46066 | H23: 46101 | I23: VA | J23: 0 | K23: Amy Marinello | L23: Kelly/Heidi | M23: 0.02 | N23: 0 | Q23: Title | R23: No | S23: No | T23: N/A | U23: Yes | Y23: Active | Z23: =IFERROR(VLOOKUP(K23,'👤 Agents'!$C$4:$D$200,2,FALSE),"") | AA23: =IFERROR(VLOOKUP(L23,'👤 Agents'!$C$4:$D$200,2,FALSE),"") | AB23: =IF(Z23="HH","Yes","No") | AC23: =IF(AA23="HH","Yes","No") | AD23: =IFERROR(IF(M23>0,M23-N23,0),0) | AE23: =IFERROR(IF(M23>0,F23*M23,IF(O23>0,O23,0)),0) | AF23: =IF(U23="Yes",399,0) | AG23: =IFERROR(IF(N23>0,F23*N23,IF(AND(AB23="Yes",O23>0),O23/2,0)),0) | AH23: =IFERROR(IF(AD23>0,F23*AD23,IF(AND(AC23="Yes",O23>0),O23/2,0)),0) | AI23: =IF(AB23="Yes",AG23,0)+IF(AC23="Yes",AH23,0)+AF23 | AJ23: =IF(AE23=0,"",IF(ABS(AE23-(AG23+AH23))<1,"✓ OK","⚠️ CHECK: Total="&TEXT(AE23,"$#,##0")&" vs Sides="&TEXT(AG23+AH23,"$#,##0")))
A24: 2026-020 | B24: 46079 | C24: 18592 Edwards #169, Doylestown 44230 | E24: 34900 | F24: 30000 | G24: 46071 | H24: 46084 | I24: CASH | J24: 0 | K24: Vicky & Beth | L24: Melissa Steiner | M24: 0 | N24: 0 | O24: 4000 | R24: No | S24: No | T24: N/A | U24: No | V24: NA | Y24: Active | Z24: =IFERROR(VLOOKUP(K24,'👤 Agents'!$C$4:$D$200,2,FALSE),"") | AA24: =IFERROR(VLOOKUP(L24,'👤 Agents'!$C$4:$D$200,2,FALSE),"") | AB24: =IF(Z24="HH","Yes","No") | AC24: =IF(AA24="HH","Yes","No") | AD24: =IFERROR(IF(M24>0,M24-N24,0),0) | AE24: =IFERROR(IF(M24>0,F24*M24,IF(O24>0,O24,0)),0) | AF24: =IF(U24="Yes",399,0) | AG24: =IFERROR(IF(N24>0,F24*N24,IF(AND(AB24="Yes",O24>0),O24/2,0)),0) | AH24: =IFERROR(IF(AD24>0,F24*AD24,IF(AND(AC24="Yes",O24>0),O24/2,0)),0) | AI24: =IF(AB24="Yes",AG24,0)+IF(AC24="Yes",AH24,0)+AF24 | AJ24: =IF(AE24=0,"",IF(ABS(AE24-(AG24+AH24))<1,"✓ OK","⚠️ CHECK: Total="&TEXT(AE24,"$#,##0")&" vs Sides="&TEXT(AG24+AH24,"$#,##0")))
A25: 2026-021 | B25: 46079 | C25: 536 Austin, Akron 44320 | E25: 134900 | F25: 134900 | G25: 46070 | H25: 46100 | I25: CONV | J25: 0 | K25: Kelly Watts | L25: Deb Shreiner | M25: 0 | N25: 0 | O25: 7070.5 | Q25: Title | R25: No | S25: No | T25: N/A | U25: Yes | V25: First Security | Y25: Active | Z25: =IFERROR(VLOOKUP(K25,'👤 Agents'!$C$4:$D$200,2,FALSE),"") | AA25: =IFERROR(VLOOKUP(L25,'👤 Agents'!$C$4:$D$200,2,FALSE),"") | AB25: =IF(Z25="HH","Yes","No") | AC25: =IF(AA25="HH","Yes","No") | AD25: =IFERROR(IF(M25>0,M25-N25,0),0) | AE25: =IFERROR(IF(M25>0,F25*M25,IF(O25>0,O25,0)),0) | AF25: =IF(U25="Yes",399,0) | AG25: =IFERROR(IF(N25>0,F25*N25,IF(AND(AB25="Yes",O25>0),O25/2,0)),0) | AH25: =IFERROR(IF(AD25>0,F25*AD25,IF(AND(AC25="Yes",O25>0),O25/2,0)),0) | AI25: =IF(AB25="Yes",AG25,0)+IF(AC25="Yes",AH25,0)+AF25 | AJ25: =IF(AE25=0,"",IF(ABS(AE25-(AG25+AH25))<1,"✓ OK","⚠️ CHECK: Total="&TEXT(AE25,"$#,##0")&" vs Sides="&TEXT(AG25+AH25,"$#,##0")))
A26: 2026-022 | B26: 46079 | C26: 349 E Hopocan, Barberton 44203 | D26: 3203612 | E26: 105000 | F26: 108000 | G26: 46075 | H26: 46108 | I26: FHA | J26: 5500 | K26: Barb Lesure | L26: Brenda Verbeka | M26: 0.07 | N26: 0.045 | P26: 500 | Q26: HH | R26: Yes | S26: Yes | T26: Buyer | U26: Yes | V26: Ohio Real Title | Y26: Active | Z26: =IFERROR(VLOOKUP(K26,'👤 Agents'!$C$4:$D$200,2,FALSE),"") | AA26: =IFERROR(VLOOKUP(L26,'👤 Agents'!$C$4:$D$200,2,FALSE),"") | AB26: =IF(Z26="HH","Yes","No") | AC26: =IF(AA26="HH","Yes","No") | AD26: =IFERROR(IF(M26>0,M26-N26,0),0) | AE26: =IFERROR(IF(M26>0,F26*M26,IF(O26>0,O26,0)),0) | AF26: =IF(U26="Yes",399,0) | AG26: =IFERROR(IF(N26>0,F26*N26,IF(AND(AB26="Yes",O26>0),O26/2,0)),0) | AH26: =IFERROR(IF(AD26>0,F26*AD26,IF(AND(AC26="Yes",O26>0),O26/2,0)),0) | AI26: =IF(AB26="Yes",AG26,0)+IF(AC26="Yes",AH26,0)+AF26 | AJ26: =IF(AE26=0,"",IF(ABS(AE26-(AG26+AH26))<1,"✓ OK","⚠️ CHECK: Total="&TEXT(AE26,"$#,##0")&" vs Sides="&TEXT(AG26+AH26,"$#,##0")))
A27: 2026-023 | B27: 46079 | C27: 12249 Whitman, Doylestown 44230 | D27: 3205909 | E27: 199900 | F27: 185500 | G27: 46076 | H27: 46118 | I27: CONV | J27: 5500 | K27: Vicky & Beth | L27: Christine Conkle | M27: 0.05 | N27: 0.03 | P27: 1000 | Q27: Other | R27: Yes | S27: Yes | T27: Seller | U27: Yes | V27: Kropf (Orrville Law) | Y27: Active | Z27: =IFERROR(VLOOKUP(K27,'👤 Agents'!$C$4:$D$200,2,FALSE),"") | AA27: =IFERROR(VLOOKUP(L27,'👤 Agents'!$C$4:$D$200,2,FALSE),"") | AB27: =IF(Z27="HH","Yes","No") | AC27: =IF(AA27="HH","Yes","No") | AD27: =IFERROR(IF(M27>0,M27-N27,0),0) | AE27: =IFERROR(IF(M27>0,F27*M27,IF(O27>0,O27,0)),0) | AF27: =IF(U27="Yes",399,0) | AG27: =IFERROR(IF(N27>0,F27*N27,IF(AND(AB27="Yes",O27>0),O27/2,0)),0) | AH27: =IFERROR(IF(AD27>0,F27*AD27,IF(AND(AC27="Yes",O27>0),O27/2,0)),0) | AI27: =IF(AB27="Yes",AG27,0)+IF(AC27="Yes",AH27,0)+AF27 | AJ27: =IF(AE27=0,"",IF(ABS(AE27-(AG27+AH27))<1,"✓ OK","⚠️ CHECK: Total="&TEXT(AE27,"$#,##0")&" vs Sides="&TEXT(AG27+AH27,"$#,##0")))
A28: 2026-024 | B28: 46079 | C28: 3179 Vanderhoof, Clinton 44216 | E28: 189900 | F28: 200000 | G28: 46075 | H28: 46115 | I28: CONV | J28: 0 | K28: Sonja Halstead | L28: Rebbecca Tessanne | M28: 0 | N28: 0 | P28: 1000 | Q28: HH | R28: No | S28: No | T28: N/A | U28: Yes | V28: First Meridian | Y28: Active | Z28: =IFERROR(VLOOKUP(K28,'👤 Agents'!$C$4:$D$200,2,FALSE),"") | AA28: =IFERROR(VLOOKUP(L28,'👤 Agents'!$C$4:$D$200,2,FALSE),"") | AB28: =IF(Z28="HH","Yes","No") | AC28: =IF(AA28="HH","Yes","No") | AD28: =IFERROR(IF(M28>0,M28-N28,0),0) | AE28: =IFERROR(IF(M28>0,F28*M28,IF(O28>0,O28,0)),0) | AF28: =IF(U28="Yes",399,0) | AG28: =IFERROR(IF(N28>0,F28*N28,IF(AND(AB28="Yes",O28>0),O28/2,0)),0) | AH28: =IFERROR(IF(AD28>0,F28*AD28,IF(AND(AC28="Yes",O28>0),O28/2,0)),0) | AI28: =IF(AB28="Yes",AG28,0)+IF(AC28="Yes",AH28,0)+AF28 | AJ28: =IF(AE28=0,"",IF(ABS(AE28-(AG28+AH28))<1,"✓ OK","⚠️ CHECK: Total="&TEXT(AE28,"$#,##0")&" vs Sides="&TEXT(AG28+AH28,"$#,##0")))

Sheet ✅ Checklist
A1: ✅ TRANSACTION CHECKLIST — Track paperwork and action items for each transaction
A2: Use the dropdown in each cell: Not Started | In Progress | Waiting | Complete | N/A
C3: CHECK PAPERWORK | S3: ACTION ITEMS | AD3: EM / COMMISSION / HW | AK3: CLOSED SALE | AP3: FALLEN SALE (BOMB)
A4: Txn ID | B4: Address | C4: MLS Printout | D4: FHA/VA Addendum | E4: Agency Disclosure | F4: Condo Addendum | G4: Consumer Guide | H4: Purchase Agreement | I4: ABA | J4: ABA (POD) | K4: Property Disclosure | L4: Home Warranty App Received | M4: EBRA | N4: Lead-Based Paint Disclosure | O4: Other Documents | P4: Home Inspection Disclosure | Q4: Anti-Fraud Disclosure | R4: Pre-Approval / Proof of Funds | S4: Change MLS Status (Our Listing) | T4: Create Sale File — ZipForms | U4: Add EBRA to ZipForms (Our Buyer) | V4: Sent to Data Entry | W4: Prestart Sent to Title Co. | X4: Scan Notice to HHMS (Our Buyer) | Y4: Log in Sales Book/Board | Z4: FB Post / Update Window Sheet (Our Listing) | AA4: Record on Rob's Spreadsheet | AB4: Register Buyer in EBRA Database | AC4: Home Warranty Ordered | AD4: Earnest Money Received & Deposited | AE4: EM Deposit Method | AF4: EM Sent to Accounting | AG4: Copy in P: Drive / ZipForms | AH4: Send Commission Invoice to Title | AI4: Manager Sales Sheet to E-Sign | AJ4: Commission Invoice — P Drive | AK4: Social Media SOLD Post | AL4: Mark Sold in MLS | AM4: Order Post Sign Down | AN4: Move to Closed — ZipForms | AO4: Take Sheet Out of Front Window | AP4: [BOMB] Change MLS Status | AQ4: [BOMB] Mutual Release to Susan Ipavec | AR4: [BOMB] Notify Title Co. | AS4: [BOMB] Coded in PP | AT4: [BOMB] Home Warranty Notified/Canceled | AU4: [BOMB] Change Status in ZipForms | AV4: [BOMB] Change Window Sheet
A5: 2026-001 | B5: =IFERROR(VLOOKUP(A5,'🗄️ Transactions'!$A:$C,3,FALSE),"") | C5: Complete | D5: Complete | E5: Complete | F5: N/A | G5: Complete | H5: Complete | I5: Complete | J5: Complete | K5: Complete | L5: Complete | M5: Complete | N5: Not Started | O5: Not Started | P5: Not Started | Q5: Not Started | R5: Not Started | S5: Not Started | T5: Not Started | U5: Not Started | V5: Not Started | W5: Not Started | X5: Not Started | Y5: Not Started | Z5: Not Started | AA5: Not Started | AB5: Not Started | AC5: Not Started | AD5: Not Started | AE5: Not Started | AF5: Not Started | AG5: Not Started | AH5: Not Started | AI5: Not Started | AJ5: Not Started | AK5: Not Started | AL5: Not Started | AM5: Not Started | AN5: Not Started | AO5: Not Started | AP5: Not Started | AQ5: Not Started | AR5: Not Started | AS5: Not Started | AT5: Not Started | AU5: Not Started | AV5: Not Started
A6: 2026-002 | B6: =IFERROR(VLOOKUP(A6,'🗄️ Transactions'!$A:$C,3,FALSE),"") | C6: Complete | D6: N/A | E6: Complete | F6: N/A | G6: Complete | H6: Complete | I6: Complete | J6: N/A | K6: Complete | L6: N/A | M6: Complete | N6: Complete | O6: Not Started | P6: N/A | Q6: Complete | R6: Complete | S6: Complete | T6: Complete | U6: Not Started | V6: Not Started | W6: Not Started | X6: Not Started | Y6: Not Started | Z6: Not Started | AA6: Not Started | AB6: Not Started | AC6: Not Started | AD6: Not Started | AE6: Not Started | AF6: Not Started | AG6: Not Started | AH6: Not Started | AI6: Not Started | AJ6: Not Started | AK6: Not Started | AL6: Not Started | AM6: Not Started | AN6: Not Started | AO6: Not Started | AP6: Not Started | AQ6: Not Started | AR6: Not Started | AS6: Not Started | AT6: Not Started | AU6: Not Started | AV6: Not Started
A7: 2026-003 | B7: =IFERROR(VLOOKUP(A7,'🗄️ Transactions'!$A:$C,3,FALSE),"") | C7: Complete | D7: N/A | E7: Complete | F7: Complete | G7: Complete | H7: Complete | I7: Complete | J7: N/A | K7: Complete | L7: Complete | M7: Complete | N7: N/A | O7: Not Started | P7: N/A | Q7: Complete | R7: Complete | S7: N/A | T7: Complete | U7: Not Started | V7: Not Started | W7: Not Started | X7: Not Started | Y7: Not Started | Z7: Not Started | AA7: Not Started | AB7: Not Started | AC7: Not Started | AD7: Not Started | AE7: Not Started | AF7: Not Started | AG7: Not Started | AH7: Not Started | AI7: Not Started | AJ7: Not Started | AK7: Not Started | AL7: Not Started | AM7: Not Started | AN7: Not Started | AO7: Not Started | AP7: Not Started | AQ7: Not Started | AR7: Not Started | AS7: Not Started | AT7: Not Started | AU7: Not Started | AV7: Not Started
A8: 2026-004 | B8: =IFERROR(VLOOKUP(A8,'🗄️ Transactions'!$A:$C,3,FALSE),"") | C8: Not Started | D8: Not Started | E8: Not Started | F8: Not Started | G8: Not Started | H8: Not Started | I8: Not Started | J8: Not Started | K8: Not Started | L8: Not Started | M8: Not Started | N8: Not Started | O8: Not Started | P8: Not Started | Q8: Not Started | R8: Not Started | S8: Not Started | T8: Not Started | U8: Not Started | V8: Not Started | W8: Not Started | X8: Not Started | Y8: Not Started | Z8: Not Started | AA8: Not Started | AB8: Not Started | AC8: Not Started | AD8: Not Started | AE8: Not Started | AF8: Not Started | AG8: Not Started | AH8: Not Started | AI8: Not Started | AJ8: Not Started | AK8: Not Started | AL8: Not Started | AM8: Not Started | AN8: Not Started | AO8: Not Started | AP8: Not Started | AQ8: Not Started | AR8: Not Started | AS8: Not Started | AT8: Not Started | AU8: Not Started | AV8: Not Started
A9: 2026-005 | B9: =IFERROR(VLOOKUP(A9,'🗄️ Transactions'!$A:$C,3,FALSE),"") | C9: Not Started | D9: Not Started | E9: Not Started | F9: Not Started | G9: Not Started | H9: Not Started | I9: Not Started | J9: Not Started | K9: Not Started | L9: Not Started | M9: Not Started | N9: Not Started | O9: Not Started | P9: Not Started | Q9: Not Started | R9: Not Started | S9: Not Started | T9: Not Started | U9: Not Started | V9: Not Started | W9: Not Started | X9: Not Started | Y9: Not Started | Z9: Not Started | AA9: Not Started | AB9: Not Started | AC9: Not Started | AD9: Not Started | AE9: Not Started | AF9: Not Started | AG9: Not Started | AH9: Not Started | AI9: Not Started | AJ9: Not Started | AK9: Not Started | AL9: Not Started | AM9: Not Started | AN9: Not Started | AO9: Not Started | AP9: Not Started | AQ9: Not Started | AR9: Not Started | AS9: Not Started | AT9: Not Started | AU9: Not Started | AV9: Not Started
A10: 2026-006 | B10: =IFERROR(VLOOKUP(A10,'🗄️ Transactions'!$A:$C,3,FALSE),"") | C10: Not Started | D10: Not Started | E10: Not Started | F10: Not Started | G10: Not Started | H10: Not Started | I10: Not Started | J10: Not Started | K10: Not Started | L10: Not Started | M10: Not Started | N10: Not Started | O10: Not Started | P10: Not Started | Q10: Not Started | R10: Not Started | S10: Not Started | T10: Not Started | U10: Not Started | V10: Not Started | W10: Not Started | X10: Not Started | Y10: Not Started | Z10: Not Started | AA10: Not Started | AB10: Not Started | AC10: Not Started | AD10: Not Started | AE10: Not Started | AF10: Not Started | AG10: Not Started | AH10: Not Started | AI10: Not Started | AJ10: Not Started | AK10: Not Started | AL10: Not Started | AM10: Not Started | AN10: Not Started | AO10: Not Started | AP10: Not Started | AQ10: Not Started | AR10: Not Started | AS10: Not Started | AT10: Not Started | AU10: Not Started | AV10: Not Started
A11: 2026-007 | B11: =IFERROR(VLOOKUP(A11,'🗄️ Transactions'!$A:$C,3,FALSE),"") | C11: Not Started | D11: Not Started | E11: Not Started | F11: Not Started | G11: Not Started | H11: Not Started | I11: Not Started | J11: Not Started | K11: Not Started | L11: Not Started | M11: Not Started | N11: Not Started | O11: Not Started | P11: Not Started | Q11: Not Started | R11: Not Started | S11: Not Started | T11: Not Started | U11: Not Started | V11: Not Started | W11: Not Started | X11: Not Started | Y11: Not Started | Z11: Not Started | AA11: Not Started | AB11: Not Started | AC11: Not Started | AD11: Not Started | AE11: Not Started | AF11: Not Started | AG11: Not Started | AH11: Not Started | AI11: Not Started | AJ11: Not Started | AK11: Not Started | AL11: Not Started | AM11: Not Started | AN11: Not Started | AO11: Not Started | AP11: Not Started | AQ11: Not Started | AR11: Not Started | AS11: Not Started | AT11: Not Started | AU11: Not Started | AV11: Not Started
A12: 2026-008 | B12: =IFERROR(VLOOKUP(A12,'🗄️ Transactions'!$A:$C,3,FALSE),"") | C12: Not Started | D12: Not Started | E12: Not Started | F12: Not Started | G12: Not Started | H12: Not Started | I12: Not Started | J12: Not Started | K12: Not Started | L12: Not Started | M12: Not Started | N12: Not Started | O12: Not Started | P12: Not Started | Q12: Not Started | R12: Not Started | S12: Not Started | T12: Not Started | U12: Not Started | V12: Not Started | W12: Not Started | X12: Not Started | Y12: Not Started | Z12: Not Started | AA12: Not Started | AB12: Not Started | AC12: Not Started | AD12: Not Started | AE12: Not Started | AF12: Not Started | AG12: Not Started | AH12: Not Started | AI12: Not Started | AJ12: Not Started | AK12: Not Started | AL12: Not Started | AM12: Not Started | AN12: Not Started | AO12: Not Started | AP12: Not Started | AQ12: Not Started | AR12: Not Started | AS12: Not Started | AT12: Not Started | AU12: Not Started | AV12: Not Started
A13: 2026-009 | B13: =IFERROR(VLOOKUP(A13,'🗄️ Transactions'!$A:$C,3,FALSE),"") | C13: Not Started | D13: Not Started | E13: Not Started | F13: Not Started | G13: Not Started | H13: Not Started | I13: Not Started | J13: Not Started | K13: Not Started | L13: Not Started | M13: Not Started | N13: Not Started | O13: Not Started | P13: Not Started | Q13: Not Started | R13: Not Started | S13: Not Started | T13: Not Started | U13: Not Started | V13: Not Started | W13: Not Started | X13: Not Started | Y13: Not Started | Z13: Not Started | AA13: Not Started | AB13: Not Started | AC13: Not Started | AD13: Not Started | AE13: Not Started | AF13: Not Started | AG13: Not Started | AH13: Not Started | AI13: Not Started | AJ13: Not Started | AK13: Not Started | AL13: Not Started | AM13: Not Started | AN13: Not Started | AO13: Not Started | AP13: Not Started | AQ13: Not Started | AR13: Not Started | AS13: Not Started | AT13: Not Started | AU13: Not Started | AV13: Not Started
A14: 2026-010 | B14: =IFERROR(VLOOKUP(A14,'🗄️ Transactions'!$A:$C,3,FALSE),"") | C14: Not Started | D14: Not Started | E14: Not Started | F14: Not Started | G14: Not Started | H14: Not Started | I14: Not Started | J14: Not Started | K14: Not Started | L14: Not Started | M14: Not Started | N14: Not Started | O14: Not Started | P14: Not Started | Q14: Not Started | R14: Not Started | S14: Not Started | T14: Not Started | U14: Not Started | V14: Not Started | W14: Not Started | X14: Not Started | Y14: Not Started | Z14: Not Started | AA14: Not Started | AB14: Not Started | AC14: Not Started | AD14: Not Started | AE14: Not Started | AF14: Not Started | AG14: Not Started | AH14: Not Started | AI14: Not Started | AJ14: Not Started | AK14: Not Started | AL14: Not Started | AM14: Not Started | AN14: Not Started | AO14: Not Started | AP14: Not Started | AQ14: Not Started | AR14: Not Started | AS14: Not Started | AT14: Not Started | AU14: Not Started | AV14: Not Started
A15: 2026-011 | B15: =IFERROR(VLOOKUP(A15,'🗄️ Transactions'!$A:$C,3,FALSE),"") | C15: Not Started | D15: Not Started | E15: Not Started | F15: Not Started | G15: Not Started | H15: Not Started | I15: Not Started | J15: Not Started | K15: Not Started | L15: Not Started | M15: Not Started | N15: Not Started | O15: Not Started | P15: Not Started | Q15: Not Started | R15: Not Started | S15: Not Started | T15: Not Started | U15: Not Started | V15: Not Started | W15: Not Started | X15: Not Started | Y15: Not Started | Z15: Not Started | AA15: Not Started | AB15: Not Started | AC15: Not Started | AD15: Not Started | AE15: Not Started | AF15: Not Started | AG15: Not Started | AH15: Not Started | AI15: Not Started | AJ15: Not Started | AK15: Not Started | AL15: Not Started | AM15: Not Started | AN15: Not Started | AO15: Not Started | AP15: Not Started | AQ15: Not Started | AR15: Not Started | AS15: Not Started | AT15: Not Started | AU15: Not Started | AV15: Not Started
A16: 2026-012 | B16: =IFERROR(VLOOKUP(A16,'🗄️ Transactions'!$A:$C,3,FALSE),"") | C16: Not Started | D16: Not Started | E16: Not Started | F16: Not Started | G16: Not Started | H16: Not Started | I16: Not Started | J16: Not Started | K16: Not Started | L16: Not Started | M16: Not Started | N16: Not Started | O16: Not Started | P16: Not Started | Q16: Not Started | R16: Not Started | S16: Not Started | T16: Not Started | U16: Not Started | V16: Not Started | W16: Not Started | X16: Not Started | Y16: Not Started | Z16: Not Started | AA16: Not Started | AB16: Not Started | AC16: Not Started | AD16: Not Started | AE16: Not Started | AF16: Not Started | AG16: Not Started | AH16: Not Started | AI16: Not Started | AJ16: Not Started | AK16: Not Started | AL16: Not Started | AM16: Not Started | AN16: Not Started | AO16: Not Started | AP16: Not Started | AQ16: Not Started | AR16: Not Started | AS16: Not Started | AT16: Not Started | AU16: Not Started | AV16: Not Started
... A28: 2026-024 | B28: =IFERROR(VLOOKUP(A28,'🗄️ Transactions'!$A:$C,3,FALSE),"") | C28: Not Started | D28: Not Started | E28: Not Started | F28: Not Started | G28: Not Started | H28: Not Started | I28: Not Started | J28: Not Started | K28: Not Started | L28: Not Started | M28: Not Started | N28: Not Started | O28: Not Started | P28: Not Started | Q28: Not Started | R28: Not Started | S28: Not Started | T28: Not Started | U28: Not Started | V28: Not Started | W28: Not Started | X28: Not Started | Y28: Not Started | Z28: Not Started | AA28: Not Started | AB28: Not Started | AC28: Not Started | AD28: Not Started | AE28: Not Started | AF28: Not Started | AG28: Not Started | AH28: Not Started | AI28: Not Started | AJ28: Not Started | AK28: Not Started | AL28: Not Started | AM28: Not Started | AN28: Not Started | AO28: Not Started | AP28: Not Started | AQ28: Not Started | AR28: Not Started | AS28: Not Started | AT28: Not Started | AU28: Not Started | AV28: Not Started

Sheet 👤 Agents
A1: 👤 AGENT DIRECTORY — Add new agents at the bottom
A2: ⚠️ DO NOT delete rows or rearrange columns. Add new agents in the YELLOW rows below.
A3: # | B3: AgentID | C3: AgentName | D3: Office
A4: 1 | B4: PH | C4: Pulte Homes | D4: Pulte Homes
A5: 2 | B5: BL | C5: Barb Lesure | D5: HH
A6: 3 | B6: IC | C6: Ivana Carson | D6: Keller
A7: 4 | B7: RE | C7: Rachel Eastwood | D7: HH
A8: 5 | B8: EY | C8: Eric Yetzer | D8: HH
A9: 6 | B9: KA | C9: Karen/Milka | D9: HH
A10: 7 | B10: KE | C10: Kelly/Heidi | D10: HH
A11: 8 | B11: MK | C11: Matthew Kalogeras | D11: Trelora
A12: 9 | B12: KA | C12: Karen/Annette | D12: HH
A13: 10 | B13: MM | C13: Mark Metz | D13: Keller
A14: 11 | B14: RT | C14: Rebbecca Tessanne | D14: HH
A15: 12 | B15: RH | C15: Ron Ho | D15: HH
... A38: 35 | B38: SH | C38: Sonja Halstead | D38: Keller Williams
A39: 36
A40: 37
A41: 38
A42: 39
A43: 40

Sheet 📋 Instructions
A1: 📋 HH REALTY TRANSACTION TRACKER — How To Use This File
A2: Designed for daily use by HH Realty staff · Keep this file saved on the network drive
B4: COLOR GUIDE — What the cell colors mean
B5: 🟡 YELLOW cell | C5: TYPE HERE — these are your entry fields
B6: 🔵 BLUE cell | C6: AUTO-CALCULATED — do not type here, formula fills it in
B7: ⚪ GREY cell | C7: LOCKED — system field, cannot be edited
B8: 🟢 GREEN (Dashboard) | C8: Key performance number, updates automatically
B9: 🔴 RED (Dashboard) | C9: Warning — needs attention
B11: STEP-BY-STEP GUIDE
B12: STEP 1 — Add a New Transaction
B13: Go to the '🏠 INPUT' sheet. Fill in every YELLOW cell. Required fields are marked with ★. Click the 'Add Transaction' button when done. The row will appear in '🗄️ TRANSACTIONS'.
B15: STEP 2 — Update Checklist Items
B16: Go to '✅ CHECKLIST'. Find the row for your transaction (search by address). Use the dropdown in each column to mark items as: Complete, In Progress, Waiting, N/A, or Not Started.
B18: STEP 3 — Edit a Transaction
B19: Go to '🗄️ TRANSACTIONS'. Find the row and click any YELLOW cell to edit. BLUE and GREY cells update automatically — do not type in them.
B21: STEP 4 — View the Dashboard
B22: Go to '📊 Dashboard'. It updates automatically every time you open the file. No need to press any buttons or refresh.
B24: STEP 5 — Add a New Agent
B25: Go to '👤 Agents'. Scroll to the bottom of the agent list. Type the agent's name in column B and their office in column C. The ID fills automatically.
B27: STEP 6 — Close or BOMB a Transaction
... B34: • If a dropdown doesn't show your agent, first add them to the '👤 Agents' sheet. • Commission %: enter as a decimal (e.g., 6% = 0.06). • If you make a mistake, press Ctrl+Z to undo. • Save the file with Ctrl+S after each entry.

Sheet ⚙️ Lookups
A1: CHECKLIST STATUS | D1: LOAN TYPE | F1: EARNEST MONEY HOLDER | H1: HOME WARRANTY PAYER | J1: YES / NO | L1: TRANSACTION STATUS
A2: Status | B2: Bucket | D2: LoanType | F2: EMHold | H2: HWPay | J2: YN | L2: TransStatus
A3: Not Started | B3: Active | D3: CONV | F3: HH | H3: Seller | J3: Yes | L3: Active
A4: In Progress | B4: Active | D4: FHA | F4: Title | H4: Buyer | J4: No | L4: Closed
A5: Waiting | B5: Active | D5: VA | F5: CoBroke | H5: Split | L5: BOMB
A6: Complete | B6: Complete | D6: CASH | F6: Buyer | H6: Other
A7: N/A | B7: N/A | D7: New Const | F7: Seller | H7: N/A
D8: Eq. Ln | F8: N/A
D9: Other | F9: Other
A15: FlatFee | B15: Amount
A16: Flat Fee Amount | B16: 399
